pep470/__about__.py
pep470/__init__.py
pep470/__main__.py
pep470/cli.py
pep470-15.0.dist-info/DESCRIPTION.rst
pep470-15.0.dist-info/entry_points.txt
pep470-15.0.dist-info/METADATA
pep470-15.0.dist-info/metadata.json
pep470-15.0.dist-info/RECORD
pep470-15.0.dist-info/top_level.txt
pep470-15.0.dist-info/WHEEL
