Metadata-Version: 2.0
Name: pep470
Version: 15.0
Summary: Script to enable downloading files for the PEP 470 migration.
Home-page: https://github.com/pypa/pep470
Author: The Python Packaging Authority
Author-email: donald@stufft.io
License: Apache License, Version 2.0
Platform: UNKNOWN
Classifier: Intended Audience :: Developers
Classifier: License :: OSI Approved :: Apache Software License
Requires-Dist: click
Requires-Dist: progress
Requires-Dist: twine
